Workbook

Sheet Items
A1: receipt_id | B1: line_no | C1: item | D1: amount_cad | E1: Code | F1: GST | G1: PST | H1: budget_category | I1: category_source | J1: raw_line
A2: 20260214_sobeys_363_95 | B2: 0 | C2: Comp Quick Oats 1KG | D2: 4.79 | E2: C | F2: 0 | G2: 0 | H2: Groceries | I2: default
A3: 20260214_sobeys_363_95 | B3: 0 | C3: Vinta Crackers | D3: 4.29 | E3: C | F3: 0 | G3: 0 | H3: Groceries | I3: exact
A4: 20260214_sobeys_363_95 | B4: 0 | C4: Candy GMS Org | D4: 3.49 | E4: BC | F4: 0.1745 | G4: 0.2443 | H4: Groceries | I4: exact
A5: 20260214_sobeys_363_95 | B5: 3 | C5: Oep Pic Med | D5: 6.49 | E5: C | F5: 0 | G5: 0 | H5: Groceries | I5: default | J5: GROCERY | $6.49
A6: 20260214_sobeys_363_95 | B6: 9 | C6: Oep Pic Med | D6: 5.99 | E6: C | F6: 0 | G6: 0 | H6: Groceries | I6: default | J6: Cep Pic Med | $6.49 | INSTANT SAVINGS -0.50
A7: 20260214_sobeys_363_95 | B7: 13 | C7: Pie Filling S/Berry | D7: 5.99 | E7: C | F7: 0 | G7: 0 | H7: Groceries | I7: exact | J7: Pie Filling S/Berry | $6.49 | INSTANT SAVINGS -0.50
A8: 20260214_sobeys_363_95 | B8: 23 | C8: Pie Filling S/Berry | D8: 6.49 | E8: C | F8: 0 | G8: 0 | H8: Groceries | I8: exact | J8: Pie Filling S/Berry | $6.49
A9: 20260214_sobeys_363_95 | B9: 37 | C9: Pretzels HoneyMustar | D9: 5.49 | E9: BC | F9: 0.2745 | G9: 0.3843 | H9: Groceries | I9: default | J9: Pretzels HoneyMustar | $1.00 |
A10: 20260214_sobeys_363_95 | B10: 43 | C10: Pretzel Cracker Rach | D10: 5.49 | E10: BC | F10: 0.2745 | G10: 0.3843 | H10: Groceries | I10: exact | J10: Pretzel Cracker Rahe | $5.49 BC
A11: 20260214_sobeys_363_95 | B11: 51 | C11: Chips Multigrain | D11: 5.29 | E11: BC | F11: 0.2645 | G11: 0.3703 | H11: Groceries | I11: exact | J11: Chips Multigrai | $5.29 BC
A12: 20260214_sobeys_363_95 | B12: 79 | C12: Chips Rstrnt Sty Lm | D12: 5.29 | E12: BC | F12: 0.2645 | G12: 0.3703 | H12: Groceries | I12: default | J12: C | $4.29
A13: 20260214_sobeys_363_95 | B13: 85 | C13: Dil Pkls Xt Grlc Snd | D13: 4.99 | E13: C | F13: 0 | G13: 0 | H13: Groceries | I13: default | J13: BC | $4.25
A14: 20260214_sobeys_363_95 | B14: 97 | C14: Pepsi Zero | D14: 4.37 | E14: BC | F14: 0.2125 | G14: 0.2975 | H14: Groceries | I14: default | J14: Pepsi Zero | $4.25 BC | EHC 0.12
A15: 20260214_sobeys_363_95 | B15: 97 | C15: Pepsi Zero | D15: 4.37 | E15: BC | F15: 0.2125 | G15: 0.2975 | H15: Groceries | I15: default | J15: Pepsi Zero | $4.25 BC | EHC 0.12
A16: 20260214_sobeys_363_95 | B16: 107 | C16: Mexican Hot Sauce | D16: 3.69 | E16: C | F16: 0 | G16: 0 | H16: Groceries | I16: exact | J16: Mexican Hot Sauce | $3.49 BC
... A66: 20260214_sobeys_363_95 | B66: 681 | C66: English Muffins Sour | D66: 3.49 | E66: C | F66: 0 | G66: 0 | H66: Groceries | I66: exact | J66: English Muffins Sour | $3.49

Sheet Receipts
A1: receipt_id | B1: order_id | C1: receipt_filename | D1: filename_total_cad | E1: subtotal_cad | F1: tax_cad | G1: total_cad | H1: parsed_item_count
A2: 20260214_sobeys_363_95 | B2: 20260214_sobeys_363_95 | C2: 20260214_sobeys_363_95.pdf | D2: 363.95 | G2: 363.95 | H2: 71

Sheet Receipt Category Totals
A1: receipt_id | B1: Child Support | C1: Autopac | D1: Car Payment | E1: Car Repair | F1: Car Replacement Fund | G1: Real Estate Tax | H1: Rental Expenses | I1: Cleaning | J1: Clothing | K1: Debt | L1: Dining | M1: Misc Paul & Rox | N1: Medical ProfSvcs | O1: University / Books | P1: Emergency Fund | Q1: Fuel | R1: Fun / Entertainment | S1: Furniture / Appliances | T1: Birthday / Celebrations | U1: Groceries | V1: IncomeTax Due | W1: Home Insurance | X1: Mortgage PrePayment | Y1: Interest Expense | Z1: Life Insurance | AA1: Medical Products | AB1: LTD Insurance | AC1: Home Mortgage | AD1: Lake | AE1: Sinking Fund | AF1: Donations | AG1: Vacation | AH1: Christmas | AI1: Home Improvement | AJ1: RRSP GIC | AK1: RRSP | AL1: Health & Fitness | AM1: Accounting | AN1: Hydro | AO1: Online Svcs | AP1: Wireless | AQ1: TV | AR1: Water | AS1: Bank Fee | AT1: MLCC | AU1: Cash/Unknown | AV1: Kids Clothing | AW1: Kids Sports | AX1: Emp Reimburse | AY1: Principal Expense | AZ1: Student Expense | BA1: Hair/Salon/Body Care | BB1: Future Use1 | BC1: Indoor Supplies | BD1: Outdoor Supplies | BE1: Future Use2 | BF1: Parking | BG1: Shareholder loan | BH1: TFSA | BI1: Asset Purchase | BJ1: Total
A2: 20260214_sobeys_363_95 | B2: =SUMIFS(Items!$D:$D,Items!$A:$A,$A2,Items!$E:$E,B1) | C2: =SUMIFS(Items!$D:$D,Items!$A:$A,$A2,Items!$E:$E,C1) | D2: =SUMIFS(Items!$D:$D,Items!$A:$A,$A2,Items!$E:$E,D1) | E2: =SUMIFS(Items!$D:$D,Items!$A:$A,$A2,Items!$E:$E,E1) | F2: =SUMIFS(Items!$D:$D,Items!$A:$A,$A2,Items!$E:$E,F1) | G2: =SUMIFS(Items!$D:$D,Items!$A:$A,$A2,Items!$E:$E,G1) | H2: =SUMIFS(Items!$D:$D,Items!$A:$A,$A2,Items!$E:$E,H1) | I2: =SUMIFS(Items!$D:$D,Items!$A:$A,$A2,Items!$E:$E,I1) | ... BI2: =SUMIFS(Items!$D:$D,Items!$A:$A,$A2,Items!$E:$E,BI1) | BJ2: =SUM(B2:BI2)

Sheet Notes
A1: note
A2: Imported manual workbook: /Users/paul/Developer/home-budget-pipeline/sobeys_one.xlsx
A3: Input path: /Users/paul/Developer/home-budget-pipeline/receipts/Sobeys
A4: Receipts parsed: 1
A5: Items parsed: 65
A6: AI Status: enabled=True, disabled_runtime=False, calls=0, batch_items=0, ai_cache_hits=0, success=0, api_errors=0.
